vpso/__init__.py
vpso/adaptation.py
vpso/ask_and_tell.py
vpso/initialization.py
vpso/math.py
vpso/mutation.py
vpso/reparation.py
vpso/termination.py
vpso/typing.py
vpso/vpso.py
vpso/vpso_constrained.py
vpso-1.1.2.dist-info/LICENSE
vpso-1.1.2.dist-info/METADATA
vpso-1.1.2.dist-info/WHEEL
vpso-1.1.2.dist-info/top_level.txt
vpso-1.1.2.dist-info/RECORD
