Metadata-Version: 2.1
Name: vpso
Version: 1.1.2
Summary: Myopic and Non-Myopic Global Optimization
Author-email: Filippo Airaldi <filippoairaldi@gmail.com>
License: MIT
Project-URL: Homepage, https://github.com/FilippoAiraldi/vectorized-particle-swarm
Project-URL: Bug Tracker, https://github.com/FilippoAiraldi/vectorized-particle-swarm/issues
Keywords: optimization,particle-swarm-optimization,adaptive,vectorization
Classifier: Programming Language :: Python
Classifier: Programming Language :: Python :: 3 :: Only
Classifier: Programming Language :: Python :: 3.9
Classifier: Programming Language :: Python :: 3.10
Classifier: Programming Language :: Python :: 3.11
Classifier: License :: OSI Approved :: MIT License
Classifier: Operating System :: OS Independent
Classifier: Intended Audience :: Science/Research
Classifier: Topic :: Scientific/Engineering :: Mathematics
Classifier: Topic :: Scientific/Engineering :: Artificial Intelligence
Requires-Python: >=3.9
License-File: LICENSE
Requires-Dist: numba >=0.57.1
Requires-Dist: scipy >=1.10.1
Requires-Dist: typing-extensions >=4.6.3
